{
    "update_time" : 100,
    "meter" : 100,
    "player_speed" : 2.5,

    "bounds" : {
        "x" : {"min":-3000, "max":3000},
        "y" : {"min":-500, "max":500}
    },
    "dead_zone" : 100,
    "scale" : 0.66,

    "objects" : [
        {"img" : "amm",  
            "path" : "./background/amm.png",  
            "x":480, "y":350, "w":450, "h":600, 
            "glow": [0,0,0]
        },

        {"img" : "coral1", 
            "path" : "./background/coral1.png", 
            "x":250, "y":380, "w":330, "h":520
        },

        {"img" : "coral2", 
            "path" : "./background/coral2.png",
            "x":120, "y":380, "w":330, "h":560
        },

        {"img" : "coral2", 
            "path" : "./background/coral2.png",
            "x":620, "y":380, "w":330, "h":560
        },

        {"img" : "urchin1", 
            "path" : "./background/coral2.png",
            "x":800, "y":500, "w":300, "h":400
        },

        {"img" : "amm", 
            "path" : "./background/coral2.png",
            "x":1100, "y":280, "w":530, "h":860,
            "glow": [0,0,0]
        },

        {"img" : "coral1", 
            "path" : "./background/coral2.png",
            "x":1400, "y":380, "w":330, "h":560
        },

        {"img" : "coral1", 
            "path" : "./background/coral2.png",
            "x":-300, "y":380, "w":330, "h":660
        },

        {"img" : "vent",   
            "path" : "./background/vent.png",
            "x":-2300, "y":430, "w":300, "h":2000, 
            "a":0, 
            "glow": [0,0,0]
        },

        {"img" : "vent",   
            "path" : "./background/vent.png",
            "x":-2500, "y":450, "w":450, "h":2000, 
            "a":0, 
            "glow": [0,0,0]
        },

        {"img" : "rock10", 
            "path" : "./background/rock10.png",
            "x":-2700, "y":445, "w":500, "h":200
        },

        {"img" : "vent",   
            "path" : "./background/vent.png",
            "x":-2700, "y":410, "w":350, "h":2000, 
            "a":0, 
            "glow": [0,0,0]
        },

        {"img" : "sub", 
            "path" : "./background/coral2.png",
            "x":2800, "y":280, "w":830, "h":660
        }
    ],

    
    "creatures" : [
        {
            "type":"mine",
            "x": 2600,
            "y": 600,
            "l": 12,
            "chain_image_path": "./background/chain.png",
            "mine_image_path": "./background/mine.png"
        },

        {
            "type":"mine",
            "x": 2000,
            "y": 600,
            "l": 16,
            "chain_image_path": "./background/chain.png",
            "mine_image_path": "./background/mine.png"
        },

        {
            "type":"kelp",
            "x": -850,
            "y": 600,
            "l": 10,
            "stalk_image_path": "./background/stalk.png"
        },

        {
            "type":"kelp",
            "x": -875,
            "y": 600,
            "l": 12,
            "stalk_image_path": "./background/stalk.png"
        },

        {
            "type":"kelp",
            "x": -920,
            "y": 600,
            "l": 6,
            "stalk_image_path": "./background/stalk.png"
        },

        {
            "type":"kelp",
            "x": -945,
            "y": 600,
            "l": 10,
            "stalk_image_path": "./background/stalk.png"
        },

        {
            "type":"kelp",
            "x": -1045,
            "y": 600,
            "l": 8,
            "stalk_image_path": "./background/stalk.png"
        },

        {
            "type":"kelp",
            "x": -1085,
            "y": 600,
            "l": 11,
            "stalk_image_path": "./background/stalk.png"
        },

        {
            "type":"kelp",
            "x": -1120,
            "y": 600,
            "l": 13,
            "stalk_image_path": "./background/stalk.png"
        },

        {
            "type":"kelp",
            "x": -1145,
            "y": 600,
            "l": 7,
            "stalk_image_path": "./background/stalk.png"
        },

        {
            "type":"kelp",
            "x": -1445,
            "y": 600,
            "l": 9,
            "stalk_image_path": "./background/stalk.png"
        },

        {
            "type":"kelp",
            "x": -1495,
            "y": 600,
            "l": 4,
            "stalk_image_path": "./background/stalk.png"
        },

        {
            "type":"kelp",
            "x": -1795,
            "y": 600,
            "l": 5,
            "stalk_image_path": "./background/stalk.png"
        },

        {
            "type":"kelp",
            "x": -800,
            "y": 600,
            "l": 8,
            "stalk_image_path": "./background/stalk.png"
        },

        {
            "type":"jellyfish",
            "x": -1400,
            "y": -650,
            "s": 200
        }
    ]
}